odoo/addons/web_touchscreen/README.rst
odoo/addons/web_touchscreen/__init__.py
odoo/addons/web_touchscreen/__manifest__.py
odoo/addons/web_touchscreen/i18n/it.po
odoo/addons/web_touchscreen/i18n/web_touchscreen.pot
odoo/addons/web_touchscreen/readme/CONTEXT.md
odoo/addons/web_touchscreen/readme/CONTRIBUTORS.md
odoo/addons/web_touchscreen/readme/CREDITS.md
odoo/addons/web_touchscreen/readme/DESCRIPTION.md
odoo/addons/web_touchscreen/readme/ROADMAP.md
odoo/addons/web_touchscreen/readme/USAGE.md
odoo/addons/web_touchscreen/static/description/icon.png
odoo/addons/web_touchscreen/static/description/index.html
odoo/addons/web_touchscreen/static/src/form_controller.esm.js
odoo_addon_web_touchscreen-16.0.1.0.1.1.dist-info/METADATA
odoo_addon_web_touchscreen-16.0.1.0.1.1.dist-info/WHEEL
odoo_addon_web_touchscreen-16.0.1.0.1.1.dist-info/top_level.txt
odoo_addon_web_touchscreen-16.0.1.0.1.1.dist-info/RECORD
